nani.py
nani-0.2.0.dist-info/DESCRIPTION.rst
nani-0.2.0.dist-info/LICENSE.txt
nani-0.2.0.dist-info/METADATA
nani-0.2.0.dist-info/RECORD
nani-0.2.0.dist-info/WHEEL
nani-0.2.0.dist-info/metadata.json
nani-0.2.0.dist-info/top_level.txt
